outdated/__init__.py
outdated/mywarnings.py
outdated/utils.py
outdated/version.py
outdated-0.2.2.dist-info/LICENSE.txt
outdated-0.2.2.dist-info/METADATA
outdated-0.2.2.dist-info/WHEEL
outdated-0.2.2.dist-info/top_level.txt
outdated-0.2.2.dist-info/RECORD
