Metadata-Version: 2.1
Name: outdated
Version: 0.2.2
Summary: Check if a version of a PyPI package is outdated
Home-page: http://github.com/alexmojaki/outdated
Author: Alex Hall
Author-email: alex.mojaki@gmail.com
License: MIT
Classifier: Intended Audience :: Developers
Classifier: Programming Language :: Python
Classifier: Programming Language :: Python :: 2
Classifier: Programming Language :: Python :: 2.7
Classifier: Programming Language :: Python :: 3
Classifier: Programming Language :: Python :: 3.5
Classifier: Programming Language :: Python :: 3.6
Classifier: Programming Language :: Python :: 3.7
Classifier: Programming Language :: Python :: 3.8
Classifier: Programming Language :: Python :: 3.9
Classifier: License :: OSI Approved :: MIT License
Classifier: Operating System :: OS Independent
Classifier: Topic :: Software Development
License-File: LICENSE.txt
